config/__init__.py
viocr/__init__.py
viocr/predict.py
viocr/train.py
viocr/loader/__init__.py
viocr/loader/aug.py
viocr/loader/dataloader.py
viocr/loader/dataloader_v1.py
viocr/model/__init__.py
viocr/model/beam.py
viocr/model/trainer.py
viocr/model/transformerocr.py
viocr/model/vocab.py
viocr/model/backbone/__init__.py
viocr/model/backbone/cnn.py
viocr/model/backbone/resnet.py
viocr/model/backbone/vgg.py
viocr/model/seqmodel/__init__.py
viocr/model/seqmodel/convseq2seq.py
viocr/model/seqmodel/seq2seq.py
viocr/model/seqmodel/transformer.py
viocr/optim/__init__.py
viocr/optim/labelsmoothingloss.py
viocr/optim/optim.py
viocr/tool/__init__.py
viocr/tool/config.py
viocr/tool/create_dataset.py
viocr/tool/logger.py
viocr/tool/predictor.py
viocr/tool/translate.py
viocr/tool/utils.py
viocr-1.0.0.dist-info/LICENSE
viocr-1.0.0.dist-info/METADATA
viocr-1.0.0.dist-info/WHEEL
viocr-1.0.0.dist-info/entry_points.txt
viocr-1.0.0.dist-info/top_level.txt
viocr-1.0.0.dist-info/RECORD
