Metadata-Version: 2.1
Name: viocr
Version: 1.0.0
Summary: Demo of a simple way to use GitHub Actions to build your Python package, bump the version number, and publish it to GitHub releases and PyPI.org all with a single click of a button in the web interface.
Home-page: https://github.com/tanthml/viocr
Project-URL: Bug Tracker, https://github.com/seanh/gha-python-packaging-demo/issues
Project-URL: Changelog, https://github.com/seanh/gha-python-packaging-demo/releases
Classifier: Programming Language :: Python :: 3
Classifier: License :: OSI Approved :: BSD License
Classifier: Intended Audience :: Developers
Requires-Python: >=3.9
License-File: LICENSE
